Metadata-Version: 2.1
Name: http-adapter
Version: 1.0.0
Summary: Python Framework.
Home-page: UNKNOWN
Author: ZhouHanLin
Author-email: zhhlvip@sina.com
License: MIT
Platform: any
Classifier: Programming Language :: Python :: 3
Classifier: License :: OSI Approved :: MIT License
Classifier: Operating System :: OS Independent
License-File: LICENCE
